aiobungie/__init__.py
aiobungie/__init__.pyi
aiobungie/api/__init__.py
aiobungie/api/framework.py
aiobungie/api/rest.py
aiobungie/builders.py
aiobungie/client.py
aiobungie/crates/__init__.py
aiobungie/crates/__init__.pyi
aiobungie/crates/activity.py
aiobungie/crates/application.py
aiobungie/crates/character.py
aiobungie/crates/clans.py
aiobungie/crates/components.py
aiobungie/crates/entity.py
aiobungie/crates/fireteams.py
aiobungie/crates/friends.py
aiobungie/crates/items.py
aiobungie/crates/milestones.py
aiobungie/crates/profile.py
aiobungie/crates/progressions.py
aiobungie/crates/records.py
aiobungie/crates/season.py
aiobungie/crates/user.py
aiobungie/error.py
aiobungie/framework.py
aiobungie/internal/__init__.py
aiobungie/internal/_backoff.py
aiobungie/internal/enums.py
aiobungie/internal/helpers.py
aiobungie/internal/time.py
aiobungie/metadata.py
aiobungie/py.typed
aiobungie/rest.py
aiobungie/traits.py
aiobungie/typedefs.py
aiobungie/url.py
aiobungie-0.5.0.dist-info/LICENSE
aiobungie-0.5.0.dist-info/METADATA
aiobungie-0.5.0.dist-info/WHEEL
aiobungie-0.5.0.dist-info/RECORD
