Metadata-Version: 2.1
Name: aiobungie
Version: 0.5.0
Summary: A Python and Asyncio API wrapper for Bungie's API.
Home-page: https://github.com/nxtlo/aiobungie
License: MIT
Keywords: async,api,destiny,destiny2,bungie
Author: nxtlo
Author-email: dhmony-99@hotmail.com
Requires-Python: >=3.10.0,<3.15
Classifier: Development Status :: 5 - Production/Stable
Classifier: Framework :: AsyncIO
Classifier: Intended Audience :: Developers
Classifier: License :: OSI Approved :: MIT License
Classifier: Natural Language :: English
Classifier: Operating System :: OS Independent
Classifier: Programming Language :: Python :: 3
Classifier: Programming Language :: Python :: 3.10
Classifier: Programming Language :: Python :: 3.11
Classifier: Programming Language :: Python :: 3.12
Classifier: Programming Language :: Python :: 3.13
Classifier: Programming Language :: Python :: 3.14
Classifier: Programming Language :: Python :: Implementation :: CPython
Classifier: Topic :: Internet :: WWW/HTTP
Classifier: Topic :: Software Development :: Libraries
Classifier: Topic :: Software Development :: Libraries :: Python Modules
Classifier: Typing :: Typed
Provides-Extra: full
Provides-Extra: speedup
Requires-Dist: aiohttp (==3.13.2)
Requires-Dist: attrs (==25.4.0)
Requires-Dist: backports-datetime-fromisoformat (==2.0.3) ; python_version == "3.10"
Requires-Dist: sain (==1.4.0)
Project-URL: Repository, https://github.com/nxtlo/aiobungie
